cjk_autojoin/__init__.py
cjk_autojoin/autojoin.py
pymdownx_cjk_autojoin-0.2.1.dist-info/WHEEL
pymdownx_cjk_autojoin-0.2.1.dist-info/METADATA
pymdownx_cjk_autojoin-0.2.1.dist-info/RECORD
