Metadata-Version: 2.3
Name: pymdownx-cjk-autojoin
Version: 0.2.1
Summary: A Python-Markdown extension to automatically join CJK characters separated by semantic line breaks.
Keywords: markdown,python-markdown,extension,cjk,japanese,chinese,korean,autojoin,typography,semantic line breaks
Author: daizutabi
Author-email: daizutabi <daizutabi@gmail.com>
License: MIT License
Classifier: Development Status :: 3 - Alpha
Classifier: Programming Language :: Python
Classifier: Programming Language :: Python :: 3 :: Only
Classifier: Programming Language :: Python :: 3.11
Classifier: Programming Language :: Python :: 3.12
Classifier: Programming Language :: Python :: 3.13
Classifier: Programming Language :: Python :: 3.14
Classifier: License :: OSI Approved :: MIT License
Classifier: Operating System :: OS Independent
Classifier: Intended Audience :: Developers
Classifier: Topic :: Text Processing :: Markup
Classifier: Topic :: Software Development :: Libraries :: Python Modules
Requires-Dist: astdoc>=1.3.2
Requires-Dist: markdown>=3
Requires-Python: >=3.11
Project-URL: Homepage, https://github.com/daizutabi/pymdownx-cjk-autojoin
Project-URL: Issues, https://github.com/daizutabi/pymdownx-cjk-autojoin/issues
Project-URL: Source, https://github.com/daizutabi/pymdownx-cjk-autojoin
